odoo10_addon_account_asset_management_method_number_end-10.0.1.0.0.99.dev3-py2.7-nspkg.pth
odoo/addons/account_asset_management_method_number_end/README.rst
odoo/addons/account_asset_management_method_number_end/__init__.py
odoo/addons/account_asset_management_method_number_end/__manifest__.py
odoo/addons/account_asset_management_method_number_end/i18n/account_asset_management_method_number_end.pot
odoo/addons/account_asset_management_method_number_end/migrations/8.0.1/pre-migrate.py
odoo/addons/account_asset_management_method_number_end/models/__init__.py
odoo/addons/account_asset_management_method_number_end/models/account_asset.py
odoo/addons/account_asset_management_method_number_end/models/account_asset_profile.py
odoo/addons/account_asset_management_method_number_end/static/description/icon.png
odoo/addons/account_asset_management_method_number_end/tests/__init__.py
odoo/addons/account_asset_management_method_number_end/tests/test_account_asset_management.py
odoo10_addon_account_asset_management_method_number_end-10.0.1.0.0.99.dev3.dist-info/METADATA
odoo10_addon_account_asset_management_method_number_end-10.0.1.0.0.99.dev3.dist-info/RECORD
odoo10_addon_account_asset_management_method_number_end-10.0.1.0.0.99.dev3.dist-info/WHEEL
odoo10_addon_account_asset_management_method_number_end-10.0.1.0.0.99.dev3.dist-info/namespace_packages.txt
odoo10_addon_account_asset_management_method_number_end-10.0.1.0.0.99.dev3.dist-info/top_level.txt
