Metadata-Version: 2.1
Name: odoo10-addon-account-asset-management-method-number-end
Version: 10.0.1.0.0.99.dev3
Summary: Financial asset management - method Number & End
Home-page: http://www.noviat.com
Author: Noviat,Odoo Community Association (OCA)
Author-email: support@odoo-community.org
License: AGPL-3
Platform: UNKNOWN
Classifier: Programming Language :: Python
Classifier: Framework :: Odoo
Classifier: License :: OSI Approved :: GNU Affero General Public License v3
Requires-Python: ~=2.7
Requires-Dist: odoo10-addon-account-asset-management
Requires-Dist: odoo (<10.1dev,>=10.0)
